FullTclash-0.1.0.dist-info/METADATA
FullTclash-0.1.0.dist-info/WHEEL
FullTclash-0.1.0.dist-info/license_files/LICENSE
fulltclash/__init__.py
fulltclash/fulltclash.cp310-win_amd64.pyd
FullTclash-0.1.0.dist-info/RECORD
